{
  "nome": "Coca-Cola 2L",
  "categoria": "bebidas",
  "preco": 12.00,
  "descricao": "Refrigerante Coca-Cola 2 Litros",
  "foto": "imagens/bebidas/coca_cola.png"
},
{
  "nome": "Coca-Cola 473ml Lata",
  "categoria": "bebidas",
  "preco": 6.00,
  "descricao": "Coca-Cola lata 473ml",
  "foto": "imagens/bebidas/coca_cola.png"
},
{
  "nome": "Coca-Cola Zero 473ml Lata",
  "categoria": "bebidas",
  "preco": 6.00,
  "descricao": "Coca-Cola Zero lata 473ml",
  "foto": "imagens/bebidas/coca_zero.png"
},
{
  "nome": "Guaraná Antarctica 2L",
  "categoria": "bebidas",
  "preco": 11.00,
  "descricao": "Refrigerante Guaraná Antarctica 2 Litros",
  "foto": "imagens/bebidas/coca_zero.png"
},
{
  "nome": "Heineken 473ml Lata",
  "categoria": "bebidas",
  "preco": 8.00,
  "descricao": "Cerveja Heineken lata 473ml",
  "foto": "imagens/bebidas/heineken.png"
},
{
  "nome": "Brahma 473ml Lata",
  "categoria": "bebidas",
  "preco": 6.00,
  "descricao": "Cerveja Brahma lata 473ml",
  "foto": "imagens/bebidas/brahma.png"
},
{
  "nome": "Spaten 473ml Lata",
  "categoria": "bebidas",
  "preco": 7.00,
  "descricao": "Cerveja Spaten lata 473ml",
  "foto": "imagens/bebidas/spaten.png"
},
{
  "nome": "Bohemia 473ml Lata",
  "categoria": "bebidas",
  "preco": 7.50,
  "descricao": "Cerveja Bohemia lata 473ml",
  "foto": "imagens/bebidas/boemia.png"
}
